NEA_CHATBOT/__init__.py
NEA_CHATBOT/main.py
NEA_CHATBOT-0.3.dist-info/LICENCE.txt
NEA_CHATBOT-0.3.dist-info/METADATA
NEA_CHATBOT-0.3.dist-info/WHEEL
NEA_CHATBOT-0.3.dist-info/top_level.txt
NEA_CHATBOT-0.3.dist-info/RECORD
