Metadata-Version: 2.1
Name: NEA-CHATBOT
Version: 0.3
Summary: A maths chatbot for my NEA
Home-page: 
Author: Swapnanil Chattopadhyay
Author-email: swapnanilchattopadhyay06@gmail.com
License: MIT
Keywords: NEA_CHATBOT
Classifier: Development Status :: 5 - Production/Stable
Classifier: Intended Audience :: Education
Classifier: Operating System :: Microsoft :: Windows :: Windows 11
Classifier: License :: OSI Approved :: MIT License
Classifier: Programming Language :: Python :: 3
License-File: LICENCE.txt
